[
        {"id": "1",
        "DistrictID":"3",
        "name": "My An Ward"},
        {"id": "2",
        "DistrictID":"3",
        "name": "Khue My Ward"},
        {"id": "3",
        "DistrictID":"3",
        "name": "Hoa Hai Ward"},
        {"id": "4",
        "DistrictID":"3",
        "name": "Hoa Quy Ward"},
       
            {"id": "5",
        "DistrictID":"1",
        "name": "Hoa Minh Ward"},
        {"id": "6",
        "DistrictID":"1",
        "name": "Hoa Khanh Nam Ward"},
        {"id": "7",
        "DistrictID":"1",
        "name": "Hoa Khanh Bac Ward"},
        {"id": "8",
        "DistrictID":"1",
        "name": "Hoa Hiep Nam Ward"},
        {"id": "9",
        "DistrictID":"1",
        "name": "Hoa Hiep Bac Ward"},

            {"id": "10",
        "DistrictID":"2",
        "name": "Binh Hien Ward"},
        {"id": "11",
        "DistrictID":"2",
        "name": "Binh Thuan Ward"},
        {"id": "12",
        "DistrictID":"2",
        "name": "Hai Chau I Ward"},
        {"id": "13",
        "DistrictID":"2",
        "name": "Hai Chau II Ward"},
        {"id": "14",
        "DistrictID":"2",
        "name": "Hoa Cuong Bac Ward"},
        {"id": "15",
        "DistrictID":"2",
        "name": "Hoa Cuong Nam Ward"},
        {"id": "16",
        "DistrictID":"2",
        "name": "Hoa Thuan Dong Ward"},
        {"id": "17",
        "DistrictID":"2",
        "name": "Hoa Thuan Tay Ward"},
        {"id": "18",
        "DistrictID":"2",
        "name": "Nam Duong Ward"},
        {"id": "19",
        "DistrictID":"2",
        "name": "Phuoc Ninh Ward"},
        {"id": "20",
        "name": "Thach Thang Ward"},
        {"id": "21",
        "DistrictID":"2",
        "name": "Thanh Binh Ward"},
        {"id": "22",
        "DistrictID":"2",
        "name": "Thuan Phuoc Ward"},
            {"id": "23",
        "DistrictID":"4",
        "name": "Tho Quang Ward"},
        {"id": "24",
        "DistrictID":"4",
        "name": "Nai Hien Dong Ward"},
        {"id": "25",
        "DistrictID":"4",
        "name": "Man Thai Ward"},
        {"id": "26",
        "DistrictID":"4",
        "name": "An Hai Bac Ward"},
        {"id": "27",
        "DistrictID":"4",
        "name": "An Hai Dong Ward"},
        {"id": "28",
        "DistrictID":"4",
        "name": "An Hai Tay Ward"},
        {"id": "29",
        "DistrictID":"4",
        "name": "Phuoc My Ward"}
]